{
  "project_info": {
    "project_number": "121087414168",
    "firebase_url": "https://flutter-notebond.firebaseio.com",
    "project_id": "flutter-notebond",
    "storage_bucket": "flutter-notebond.appspot.com"
  },
  "client": [
    {
      "client_info": {
        "mobilesdk_app_id": "1:121087414168:android:3df0c87562d5ba3e3ce5ed",
        "android_client_info": {
          "package_name": "com.bwa.bwa_learning"
        }
      },
      "oauth_client": [
        {
          "client_id": "121087414168-0krm3vepaj68app6rrn6k9urv57p1i4q.apps.googleusercontent.com",
          "client_type": 3
        }
      ],
      "api_key": [
        {
          "current_key": "AIzaSyDgjE1wl6WgfrxhHWNTddayJDhN-9rNCj8"
        }
      ],
      "services": {
        "appinvite_service": {
          "other_platform_oauth_client": [
            {
              "client_id": "121087414168-0krm3vepaj68app6rrn6k9urv57p1i4q.apps.googleusercontent.com",
              "client_type": 3
            }
          ]
        }
      }
    },
    {
      "client_info": {
        "mobilesdk_app_id": "1:121087414168:android:f44294604074bd2f",
        "android_client_info": {
          "package_name": "com.example.note_log"
        }
      },
      "oauth_client": [
        {
          "client_id": "121087414168-0krm3vepaj68app6rrn6k9urv57p1i4q.apps.googleusercontent.com",
          "client_type": 3
        }
      ],
      "api_key": [
        {
          "current_key": "AIzaSyDgjE1wl6WgfrxhHWNTddayJDhN-9rNCj8"
        }
      ],
      "services": {
        "appinvite_service": {
          "other_platform_oauth_client": [
            {
              "client_id": "121087414168-0krm3vepaj68app6rrn6k9urv57p1i4q.apps.googleusercontent.com",
              "client_type": 3
            }
          ]
        }
      }
    }
  ],
  "configuration_version": "1"
}